<annotation>
	<folder>Train</folder>
	<filename>F0-5-1.jpg</filename>
	<path>/media/ysabri/A02843E92843BCD2/Users/hacoo/Desktop/CS506/dora/dora/rocks/Train/F0-5-1.jpg</path>
	<source>
		<database>Unknown</database>
	</source>
	<size>
		<width>800</width>
		<height>415</height>
		<depth>3</depth>
	</size>
	<segmented>0</segmented>
	<object>
		<name>Rocks</name>
		<pose>Unspecified</pose>
		<truncated>1</truncated>
		<difficult>0</difficult>
		<bndbox>
			<xmin>403</xmin>
			<ymin>361</ymin>
			<xmax>590</xmax>
			<ymax>415</ymax>
		</bndbox>
	</object>
</annotation>
